magic_link/__init__.py
magic_link/config.py
magic_link/errors.py
magic_link/interfaces.py
magic_link/logging.py
magic_link/service.py
magic_link/token_engine.py
magic_link/cli/__init__.py
magic_link/cli/config.py
magic_link/cli/test_email.py
magic_link/mailer/__init__.py
magic_link/mailer/smtp.py
magic_link/storage/__init__.py
magic_link/storage/in_memory.py
magic_link/storage/redis.py
magic_link/storage/sqlalchemy.py
magic_link-1.0.0.dist-info/licenses/LICENSE
magic_link-1.0.0.dist-info/METADATA
magic_link-1.0.0.dist-info/WHEEL
magic_link-1.0.0.dist-info/entry_points.txt
magic_link-1.0.0.dist-info/top_level.txt
magic_link-1.0.0.dist-info/RECORD
